{
    "@context": "http://iiif.io/api/presentation/2/context.json",
    "@id": "https://example.org/iiif/collection/publisher",
    "@type": "sc:Collection",
    "label": {
        "en": "Online Resources from Internet Archive",
        "fa": "منابع آنلاین از (آرشیو اینترنتی)"
    },
    "license": "http://creativecommons.org/licenses/by-nc/4.0/",
    "logo": "https://pbs.twimg.com/profile_images/1618734410865459200/NyWpyMqQ_400x400.jpg",
    "metadata": [
        {
            "label": {
                "en": "Publisher",
                "fa": "ناشر"
            },
            "value": {
                "en": "[Publisher Name]",
                "fa": "[نام ناشر]"
            }
        },
        {
            "label": {
                "en": "Source",
                "fa": "منبع"
            },
            "value": {
                "en": "Internet Archive",
                "fa": "آرشیو اینترنتی"
            }
        }
    ],
    "viewingHint": "top",
    "manifests": [
        {
            "@id": "https://iiif.archivelab.org/iiif/book1_id/manifest.json",
            "@type": "sc:Manifest",
            "label": {
                "en": "Single-Volume Book 1",
                "fa": "کتاب تک جلدی ۱"
            },
            "metadata": [
                {
                    "label": {
                        "en": "Publication Date",
                        "fa": "تاریخ انتشار"
                    },
                    "value": "1895"
                },
                {
                    "label": {
                        "en": "Subject",
                        "fa": "موضوع"
                    },
                    "value": {
                        "en": "Voyages to Persia",
                        "fa": "سفرها به ایران"
                    }
                },
                {
                    "label": {
                        "en": "Internet Archive Page",
                        "fa": "صفحه در آرشیو اینترنتی"
                    },
                    "value": "https://archive.org/details/book1_id"
                }
            ],
            "viewingHint": "paged"
        },
        {
            "id": "https://iiif.archive.org/iiif/3/throughpersiabyc00arno_0/manifest.json",
            "type": "Manifest",
            "label": {
                "en": [
                    "Through Persia by caravan"
                ],
                "fa": [
                    "با کاروان از ميان سرزمين ايران"
                ]
            },
            "viewingHint": "paged",
            "metadata": [
                {
                    "label": {
                        "en": [
                            "Title"
                        ]
                    },
                    "value": {
                        "en": "Through Persia by caravan",
                        "fa": "با کاروان از ميان سرزمين ايران"
                    }
                },
                {
                    "label": {
                        "en": [
                            "Author"
                        ]
                    },
                    "value": {
                        "en": [
                            "Arnold, Arthur, Sir"
                        ]
                    }
                },
                {
                    "label": {
                        "en": "Date"
                    },
                    "value": {
                        "en": "circa 1877"
                    }
                },
                {
                    "label": {
                        "en": "Genre"
                    },
                    "value": {
                        "en": [
                            "300266481"
                        ]
                    }
                },
                {
                    "label": {
                        "en": [
                            "HasImages",
                            "hasEngraves",
                            "hasMaps"
                        ]
                    },
                    "value": {
                        "en": [
                            "true",
                            "false",
                            "false"
                        ]
                    }
                }
            ]
        },
        {
            "id": "https://iiif.archive.org/iiif/3/throughpersiaons00sykerich/manifest.json",
            "type": "Manifest",
            "label": {
                "en": [
                    "Through Persia on a side-saddle"
                ]
            },
            "viewingHint": "paged",
            "metadata": [
                {
                    "label": {
                        "en": [
                            "Title"
                        ]
                    },
                    "value": {
                        "en": "Through Persia on a side-saddle",
                        "fa": "سراسر ایران بر پشت زین اسب"
                    }
                },
                {
                    "label": {
                        "en": [
                            "Author"
                        ]
                    },
                    "value": {
                        "en": [
                            "Sykes, Ella C "
                        ]
                    }
                },
                {
                    "label": {
                        "en": "Date"
                    },
                    "value": {
                        "en": "circa 1898"
                    }
                },
                {
                    "label": {
                        "en": [
                            "HasImages",
                            "hasEngraves",
                            "hasMaps"
                        ]
                    },
                    "value": {
                        "en": [
                            "true",
                            "false",
                            "false"
                        ]
                    }
                },
                {
                    "id": "https://iiif.archive.org/iiif/3/in.gov.ignca.11918/manifest.json",
                    "type": "Manifest",
                    "label": {
                        "en": [
                            "Persia and the persian question vol.1"
                        ]
                    },
                    "viewingHint": "paged",
                    "metadata": [
                        {
                            "label": {
                                "en": "Title"
                            },
                            "value": {
                                "en": "Persia and the persian question vol.1"
                            }
                        },
                        {
                            "label": {
                                "en": [
                                    "Author"
                                ]
                            },
                            "value": {
                                "en": [
                                    "Curzon, George N"
                                ]
                            }
                        },
                        {
                            "label": {
                                "en": [
                                    "Date"
                                ]
                            },
                            "value": {
                                "en": [
                                    "circa 1892"
                                ]
                            }
                        },
                        {
                            "label": {
                                "en": [
                                    "HasImages",
                                    "hasEngraves",
                                    "hasMaps"
                                ]
                            },
                            "value": {
                                "en": [
                                    "true",
                                    "false",
                                    "true"
                                ]
                            }
                        }
                    ]
                },
                {
                    "id": "https://iiif.archive.org/iiif/3/in.gov.ignca.11917/manifest.json",
                    "type": "Manifest",
                    "label": {
                        "en": [
                            "Persia and the persian question vol.2"
                        ]
                    },
                    "viewingHint": "paged",
                    "metadata": [
                        {
                            "label": {
                                "en": "Title"
                            },
                            "value": {
                                "en": "Persia and the persian question vol.2"
                            }
                        },
                        {
                            "label": {
                                "en": [
                                    "Author"
                                ]
                            },
                            "value": {
                                "en": [
                                    "Curzon, George N"
                                ]
                            }
                        },
                        {
                            "label": {
                                "en": [
                                    "Date"
                                ]
                            },
                            "value": {
                                "en": [
                                    "circa 1892"
                                ]
                            }
                        },
                        {
                            "label": {
                                "en": [
                                    "HasImages",
                                    "hasEngraves",
                                    "hasMaps"
                                ]
                            },
                            "value": {
                                "en": [
                                    "true",
                                    "false",
                                    "true"
                                ]
                            }
                        }
                    ]
                }
            ]
        },
        {
            "id": "https://iiif.archive.org/iiif/3/in.gov.ignca.11918/manifest.json",
            "type": "Manifest",
            "label": {
                "en": [
                    "Persia and the persian question vol.1"
                ]
            },
            "viewingHint": "paged",
            "metadata": [
                {
                    "label": {
                        "en": "Title"
                    },
                    "value": {
                        "en": "Persia and the persian question vol.1"
                    }
                },
                {
                    "label": {
                        "en": [
                            "Author"
                        ]
                    },
                    "value": {
                        "en": [
                            "Curzon, George N"
                        ]
                    }
                },
                {
                    "label": {
                        "en": [
                            "Date"
                        ]
                    },
                    "value": {
                        "en": [
                            "circa 1892"
                        ]
                    }
                },
                {
                    "label": {
                        "en": [
                            "HasImages",
                            "hasEngraves",
                            "hasMaps"
                        ]
                    },
                    "value": {
                        "en": [
                            "true",
                            "false",
                            "true"
                        ]
                    }
                }
            ]
        },
        {
            "id": "https://iiif.archive.org/iiif/3/in.gov.ignca.11917/manifest.json",
            "type": "Manifest",
            "label": {
                "en": [
                    "Persia and the persian question vol.2"
                ]
            },
            "viewingHint": "paged",
            "metadata": [
                {
                    "label": {
                        "en": "Title"
                    },
                    "value": {
                        "en": "Persia and the persian question vol.2"
                    }
                },
                {
                    "label": {
                        "en": [
                            "Author"
                        ]
                    },
                    "value": {
                        "en": [
                            "Curzon, George N"
                        ]
                    }
                },
                {
                    "label": {
                        "en": [
                            "Date"
                        ]
                    },
                    "value": {
                        "en": [
                            "circa 1892"
                        ]
                    }
                },
                {
                    "label": {
                        "en": [
                            "HasImages",
                            "hasEngraves",
                            "hasMaps"
                        ]
                    },
                    "value": {
                        "en": [
                            "true",
                            "false",
                            "true"
                        ]
                    }
                }
            ]
        },
        {
            "id": "https://iiif.archive.org/iiif/3/persiaitspeople00syke/manifest.json",
            "type": "Manifest",
            "label": {
                "en": [
                    "Persia and its people"
                ]
            },
            "viewingHint": "paged",
            "metadata": [
                {
                    "label": {
                        "en": "Title"
                    },
                    "value": {
                        "en": "Persia and its people"
                    }
                },
                {
                    "label": {
                        "en": [
                            "Author"
                        ]
                    },
                    "value": {
                        "en": [
                            "Sykes, Ella Constance"
                        ]
                    }
                },
                {
                    "label": {
                        "en": [
                            "Date"
                        ]
                    },
                    "value": {
                        "en": [
                            "circa 1910"
                        ]
                    }
                },
                {
                    "label": {
                        "en": [
                            "HasImages",
                            "hasEngraves",
                            "hasMaps"
                        ]
                    },
                    "value": {
                        "en": [
                            "true",
                            "false",
                            "true"
                        ]
                    }
                }
            ]
        },
        {
            "id": "https://iiif.archive.org/iiif/3/persiaawakeninge00cresrich/manifest.json",
            "type": "Manifest",
            "label": {
                "en": [
                    "Persia, the awakening East"
                ]
            },
            "viewingHint": "paged",
            "metadata": [
                {
                    "label": {
                        "en": "Title"
                    },
                    "value": {
                        "en": "Persia, the awakening East"
                    }
                },
                {
                    "label": {
                        "en": [
                            "Author"
                        ]
                    },
                    "value": {
                        "en": [
                            "Cresson, W. Penn"
                        ]
                    }
                },
                {
                    "label": {
                        "en": [
                            "Date"
                        ]
                    },
                    "value": {
                        "en": [
                            "circa 1908"
                        ]
                    }
                },
                {
                    "label": {
                        "en": [
                            "HasImages",
                            "hasEngraves",
                            "hasMaps"
                        ]
                    },
                    "value": {
                        "en": [
                            "true",
                            "false",
                            "true"
                        ]
                    }
                }
            ]
        },
        {
            "id": "https://iiif.archive.org/iiif/3/peepsintopersia00hermrich/manifest.json",
            "type": "Manifest",
            "label": {
                "en": [
                    "Peeps into Persia"
                ]
            },
            "viewingHint": "paged",
            "metadata": [
                {
                    "label": {
                        "en": "Title"
                    },
                    "value": {
                        "en": "Peeps into Persia"
                    }
                },
                {
                    "label": {
                        "en": [
                            "Author"
                        ]
                    },
                    "value": {
                        "en": [
                            "Hermalle, Dorothy, Baroness d"
                        ]
                    }
                },
                {
                    "label": {
                        "en": [
                            "Date"
                        ]
                    },
                    "value": {
                        "en": [
                            "circa 1913"
                        ]
                    }
                },
                {
                    "label": {
                        "en": [
                            "HasImages",
                            "hasEngraves",
                            "hasMaps"
                        ]
                    },
                    "value": {
                        "en": [
                            "true",
                            "false",
                            "true"
                        ]
                    }
                }
            ]
        }
    ],
    "collections": [
        {
            "@id": "https://example.org/iiif/collection/multivolume1",
            "@type": "sc:Collection",
            "label": {
                "en": "Multi-Volume Work 1",
                "fa": "کتاب چند جلدی ۱"
            },
            "metadata": [
                {
                    "label": {
                        "en": "Title",
                        "fa": "عنوان"
                    },
                    "value": {
                        "en": "Persia and the persian question",
                        "fa": "ايران و سوال ايرانی"
                    }
                },
                {
                    "label": {
                        "en": "Internet Archive Page",
                        "fa": "صفحه در آرشیو اینترنتی"
                    },
                    "value": "https://archive.org/details/multivolume1_id"
                }
            ],
            "viewingHint": "multi-part",
            "manifests": [
                {
                    "id": "https://iiif.archive.org/iiif/3/in.gov.ignca.11918/manifest.json",
                    "type": "Manifest",
                    "label": {
                        "en": [
                            "Persia and the persian question vol.1"
                        ]
                    },
                    "metadata": [
                        {
                            "label": {
                                "en": "Title"
                            },
                            "value": {
                                "en": "Persia and the persian question vol.1"
                            }
                        },
                        {
                            "label": {
                                "en": [
                                    "Author"
                                ]
                            },
                            "value": {
                                "en": [
                                    "Curzon, George N"
                                ]
                            }
                        },
                        {
                            "label": {
                                "en": [
                                    "Date"
                                ]
                            },
                            "value": {
                                "en": [
                                    "circa 1892"
                                ]
                            }
                        },
                        {
                            "label": {
                                "en": [
                                    "HasImages",
                                    "hasEngraves",
                                    "hasMaps"
                                ]
                            },
                            "value": {
                                "en": [
                                    "true",
                                    "false",
                                    "true"
                                ]
                            }
                        }
                    ]
                },
                {
                    "id": "https://iiif.archive.org/iiif/3/in.gov.ignca.11917/manifest.json",
                    "type": "Manifest",
                    "label": {
                        "en": [
                            "Persia and the persian question vol.2"
                        ]
                    },
                    "metadata": [
                        {
                            "label": {
                                "en": "Title"
                            },
                            "value": {
                                "en": "Persia and the persian question vol.2"
                            }
                        },
                        {
                            "label": {
                                "en": [
                                    "Author"
                                ]
                            },
                            "value": {
                                "en": [
                                    "Curzon, George N"
                                ]
                            }
                        },
                        {
                            "label": {
                                "en": [
                                    "Date"
                                ]
                            },
                            "value": {
                                "en": [
                                    "circa 1892"
                                ]
                            }
                        },
                        {
                            "label": {
                                "en": [
                                    "HasImages",
                                    "hasEngraves",
                                    "hasMaps"
                                ]
                            },
                            "value": {
                                "en": [
                                    "true",
                                    "false",
                                    "true"
                                ]
                            }
                        }
                    ]
                }
            ]
        }
    ]
}